online_store/__init__.py
online_store/__main__.py
online_store/order_management.py
online_store/user_management.py
online_store_bertollo-0.1.3.dist-info/METADATA
online_store_bertollo-0.1.3.dist-info/WHEEL
online_store_bertollo-0.1.3.dist-info/entry_points.txt
online_store_bertollo-0.1.3.dist-info/top_level.txt
online_store_bertollo-0.1.3.dist-info/RECORD
